yasfpy/__init__.py
yasfpy/computers/computer.py
yasfpy/computers/computer_cpu.py
yasfpy/computers/computer_cuda.py
yasfpy/functions/__init__.py
yasfpy/functions/cpu_numba.py
yasfpy/functions/cuda_numba.py
yasfpy/functions/legendre_normalized_trigon.py
yasfpy/functions/material_handler.py
yasfpy/functions/misc.py
yasfpy/functions/spherical_functions_trigon.py
yasfpy/functions/t_entry.py
yasfpy/initial_field.py
yasfpy/log.py
yasfpy/numerics.py
yasfpy/optics.py
yasfpy/parameters.py
yasfpy/particles.py
yasfpy/simulation.py
yasfpy/solver.py
yasfpy/yasf.py
yasfpy-0.0.13.dist-info/LICENSE
yasfpy-0.0.13.dist-info/METADATA
yasfpy-0.0.13.dist-info/WHEEL
yasfpy-0.0.13.dist-info/RECORD
