Metadata-Version: 2.1
Name: yasfpy
Version: 0.0.13
Summary: Light scattering code using T-Matrix
License: MIT
Author: Mirza Arnaut
Author-email: mirza.arnaut@tu-dortmund.de
Requires-Python: >=3.10,<4.0
Classifier: License :: OSI Approved :: MIT License
Classifier: Programming Language :: Python :: 3
Classifier: Programming Language :: Python :: 3.10
Classifier: Programming Language :: Python :: 3.11
Classifier: Programming Language :: Python :: 3.12
Requires-Dist: icc-rt (>=2020.0.133,<2021.0.0)
Requires-Dist: numba (>=0.58.0,<0.59.0)
Requires-Dist: numpy (>=1.26.3,<2.0.0)
Requires-Dist: pandas (>=1.3.5,<2.0.0)
Requires-Dist: pywigxjpf (>=1.11,<2.0)
Requires-Dist: pyyaml (>=6.0.1,<7.0.0)
Requires-Dist: refractiveindex (>=0.0.3,<0.0.4)
Requires-Dist: requests (>=2.31.0,<3.0.0)
Requires-Dist: scipy (>=1.13.0,<2.0.0)
